Metadata-Version: 2.1
Name: thug-memes
Version: 0.1.2
Summary: command line tool for creating awesome thug memes
Home-page: https://github.com/jerry-git/thug-memes
Author: Jerry Pussinen
Author-email: jerry.pussinen@gmail.com
License: UNKNOWN
Platform: UNKNOWN
Classifier: License :: OSI Approved :: MIT License
Classifier: Programming Language :: Python
Classifier: Programming Language :: Python :: 3
Classifier: Programming Language :: Python :: 3.4
Classifier: Programming Language :: Python :: 3.5
Classifier: Programming Language :: Python :: 3.6
Classifier: Programming Language :: Python :: 3.7
Provides-Extra: dlib
